odoo8_addon_hr_timesheet_task_required-8.0.1.0.0.99.dev2-py2.7-nspkg.pth
odoo8_addon_hr_timesheet_task_required-8.0.1.0.0.99.dev2.dist-info/DESCRIPTION.rst
odoo8_addon_hr_timesheet_task_required-8.0.1.0.0.99.dev2.dist-info/METADATA
odoo8_addon_hr_timesheet_task_required-8.0.1.0.0.99.dev2.dist-info/RECORD
odoo8_addon_hr_timesheet_task_required-8.0.1.0.0.99.dev2.dist-info/WHEEL
odoo8_addon_hr_timesheet_task_required-8.0.1.0.0.99.dev2.dist-info/metadata.json
odoo8_addon_hr_timesheet_task_required-8.0.1.0.0.99.dev2.dist-info/namespace_packages.txt
odoo8_addon_hr_timesheet_task_required-8.0.1.0.0.99.dev2.dist-info/top_level.txt
odoo_addons/hr_timesheet_task_required/README.rst
odoo_addons/hr_timesheet_task_required/__init__.py
odoo_addons/hr_timesheet_task_required/__openerp__.py
odoo_addons/hr_timesheet_task_required/i18n/hr_timesheet_task_required.pot
odoo_addons/hr_timesheet_task_required/static/description/icon.png
odoo_addons/hr_timesheet_task_required/static/src/js/hr_timesheet_widget.js
odoo_addons/hr_timesheet_task_required/views/hr_timesheet_task_required.xml
odoo_addons/hr_timesheet_task_required/views/hr_timesheet_view.xml
