Metadata-Version: 2.0
Name: odoo8-addon-hr-timesheet-task-required
Version: 8.0.1.0.0.99.dev2
Summary: Set task on timesheet as a mandatory field
Home-page: https://acsone.eu/
Author: ACSONE SA/NV,Odoo Community Association (OCA)
Author-email: support@odoo-community.org
License: AGPL-3
Platform: UNKNOWN
Classifier: Programming Language :: Python
Classifier: Framework :: Odoo
Classifier: License :: OSI Approved :: GNU Affero General Public License v3
Requires-Python: ~=2.7
Requires-Dist: odoo (<9.0a,>=8.0a)
Requires-Dist: odoo8-addon-hr-timesheet-task
